mcp_stata/__init__.py
mcp_stata/__main__.py
mcp_stata/_native_ops.abi3.so
mcp_stata/config.py
mcp_stata/discovery.py
mcp_stata/graph_detector.py
mcp_stata/models.py
mcp_stata/native_ops.py
mcp_stata/server.py
mcp_stata/sessions.py
mcp_stata/smcl/smcl2html.py
mcp_stata/stata_client.py
mcp_stata/streaming_io.py
mcp_stata/test_stata.py
mcp_stata/ui_http.py
mcp_stata/utils.py
mcp_stata/worker.py
mcp_stata-1.23.1.dist-info/METADATA
mcp_stata-1.23.1.dist-info/WHEEL
mcp_stata-1.23.1.dist-info/entry_points.txt
mcp_stata-1.23.1.dist-info/licenses/LICENSE
mcp_stata-1.23.1.dist-info/RECORD
