Metadata-Version: 2.4
Name: mcp-stata
Version: 1.23.1
Classifier: Development Status :: 4 - Beta
Classifier: Intended Audience :: Science/Research
Classifier: Intended Audience :: Developers
Classifier: Topic :: Scientific/Engineering :: Information Analysis
Classifier: License :: OSI Approved :: GNU Affero General Public License v3 or later (AGPLv3+)
Classifier: Programming Language :: Python :: 3.11
Classifier: Programming Language :: Python :: 3.12
Classifier: Programming Language :: Python :: 3.13
Classifier: Programming Language :: Python :: 3.14
Requires-Dist: mcp[cli]>=1.0.0
Requires-Dist: pandas>=2.0.0
Requires-Dist: numpy>=1.26.0
Requires-Dist: pydantic>=2.0.0
Requires-Dist: stata-setup>=0.1.0
Requires-Dist: httpx>=0.27.0,<0.28.0
Requires-Dist: pytest-asyncio>=1.3.0
Requires-Dist: pyarrow>=14.0.0
Requires-Dist: polars>=1.36.1
Requires-Dist: build>=1.3.0 ; extra == 'dev'
Requires-Dist: hatch>=1.16.2 ; extra == 'dev'
Requires-Dist: twine>=6.2.0 ; extra == 'dev'
Requires-Dist: ruff>=0.4.0 ; extra == 'dev'
Requires-Dist: pytest>=7.0.0 ; extra == 'dev'
Requires-Dist: pytest-cov>=4.0.0 ; extra == 'dev'
Requires-Dist: pytest-xdist>=3.5.0 ; extra == 'dev'
Requires-Dist: pytest-timeout>=2.3.1 ; extra == 'dev'
Requires-Dist: python-semantic-release>=9.8.0 ; extra == 'dev'
Requires-Dist: maturin>=1.11.5 ; extra == 'dev'
Provides-Extra: dev
License-File: LICENSE
Summary:  A lightweight Model Context Protocol (MCP) server for Stata. Execute commands, inspect data, retrieve stored results (`r()`/`e()`), and view graphs in your chat interface. Built for economists who want to integrate LLM assistance into their Stata workflow. 
Keywords: mcp,stata,statistics,econometrics,ai,llm
Author-email: Thomas Monk <t.d.monk@lse.ac.uk>
License-Expression: AGPL-3.0-or-later
Requires-Python: >=3.11
Project-URL: Homepage, https://github.com/tmonk/mcp-stata
Project-URL: Issues, https://github.com/tmonk/mcp-stata/issues
Project-URL: Repository, https://github.com/tmonk/mcp-stata
